bindata/__init__.py
bindata/_generate_simulvals.py
bindata/_simuvals_class.py
bindata/bindata.py
bindata/check_commonprob.py
bindata/simul_commonprob.py
bindata/res/binary.png
bindata/res/simulvals.pickle
bindata/tests/__init__.py
bindata/tests/test_all.py
bindata-1.0.0.dist-info/LICENSE.txt
bindata-1.0.0.dist-info/METADATA
bindata-1.0.0.dist-info/WHEEL
bindata-1.0.0.dist-info/top_level.txt
bindata-1.0.0.dist-info/RECORD
