Metadata-Version: 2.2
Name: bindata
Version: 1.0.0
Summary: A library for sampling correlated binary variates.
Home-page: https://github.com/LucaMingarelli/bindata
Author: Luca Mingarelli
Author-email: lucamingarelli@me.com
License: MIT
Classifier: Programming Language :: Python :: 3
Classifier: License :: OSI Approved :: MIT License
Classifier: Operating System :: OS Independent
Requires-Python: >=3.6
License-File: LICENSE.txt
Requires-Dist: numpy
Requires-Dist: scipy
Requires-Dist: tqdm
Dynamic: author
Dynamic: author-email
Dynamic: classifier
Dynamic: description
Dynamic: description-content-type
Dynamic: home-page
Dynamic: license
Dynamic: requires-dist
Dynamic: requires-python
Dynamic: summary
